MANIFEST.in
README.txt
setup.py
ipt/__init__.py
ipt/att.py
ipt/logit.py
ipt/ols.py
ipt.egg-info/PKG-INFO
ipt.egg-info/SOURCES.txt
ipt.egg-info/dependency_links.txt
ipt.egg-info/not-zip-safe
ipt.egg-info/requires.txt
ipt.egg-info/top_level.txt