Metadata-Version: 1.1
Name: ipt
Version: 0.2.3
Summary: Probability Tilting Methods (IPT) for Causal Inference
Home-page: http://github.com/bryangraham/ipt
Author: Bryan S. Graham
Author-email: bgraham@econ.berkeley.edu
License: MIT
Keywords: Inverse Probability Tilting (IPT),Auxiliary-to-Study Tilting (AST)
Platform: UNKNOWN
Classifier: Development Status :: 3 - Alpha
Classifier: License :: OSI Approved :: MIT License
Classifier: Programming Language :: Python :: 2.7
Classifier: Topic :: Scientific/Engineering :: Mathematics
Classifier: Intended Audience :: Science/Research
